diagrams_mcp/__init__.py
diagrams_mcp/core/__init__.py
diagrams_mcp/core/formatters.py
diagrams_mcp/core/icon_manager.py
diagrams_mcp/core/node_registry.py
diagrams_mcp/core/validators.py
diagrams_mcp/http_server.py
diagrams_mcp/server.py
diagrams_mcp/tools/__init__.py
diagrams_mcp/tools/core.py
diagrams_mcp-1.0.0.dist-info/WHEEL
diagrams_mcp-1.0.0.dist-info/entry_points.txt
diagrams_mcp-1.0.0.dist-info/METADATA
diagrams_mcp-1.0.0.dist-info/RECORD
