Metadata-Version: 2.4
Name: diagrams-mcp
Version: 1.0.0
Summary: MCP server for generating infrastructure and architecture diagrams as code using the Python diagrams library
Keywords: mcp,diagrams,architecture,infrastructure,cloud,aws,azure,gcp,kubernetes,devops,graphviz
Author: Akshay Petta
Author-email: Akshay Petta <33671231+apetta@users.noreply.github.com>
License-Expression: MIT
Classifier: Development Status :: 5 - Production/Stable
Classifier: Intended Audience :: Developers
Classifier: License :: OSI Approved :: MIT License
Classifier: Programming Language :: Python :: 3
Classifier: Programming Language :: Python :: 3.11
Classifier: Programming Language :: Python :: 3.12
Classifier: Programming Language :: Python :: 3.13
Classifier: Topic :: Software Development :: Libraries :: Python Modules
Classifier: Topic :: System :: Systems Administration
Requires-Dist: fastmcp~=2.13.0
Requires-Dist: diagrams~=0.24.4
Requires-Dist: pydantic~=2.12.3
Requires-Dist: pillow>=10.0.0
Requires-Dist: requests>=2.31.0
Requires-Dist: aiofiles>=23.2.0
Requires-Dist: pytest>=8.0.0 ; extra == 'dev'
Requires-Dist: pytest-asyncio>=0.23.0 ; extra == 'dev'
Requires-Dist: pytest-cov>=4.1.0 ; extra == 'dev'
Requires-Dist: ruff>=0.3.0 ; extra == 'dev'
Requires-Python: >=3.11
Provides-Extra: dev
